pykorean/__init__.py
pykorean/main.py
pykorean-0.1.0.dist-info/WHEEL
pykorean-0.1.0.dist-info/entry_points.txt
pykorean-0.1.0.dist-info/METADATA
pykorean-0.1.0.dist-info/RECORD
