Metadata-Version: 2.1
Name: pykorean
Version: 0.1.0
Summary: 
Author: codemke
Author-email: altoformula@gmail.com
Requires-Python: >=3.11,<4.0
Classifier: Programming Language :: Python :: 3
Classifier: Programming Language :: Python :: 3.11
Requires-Dist: pytest (>=7.2.1,<8.0.0)
